[{"question": "What are Sans and Papyrus named after in &quot;Undertale&quot;?", "correct_answer": "Fonts", "incorrect_answers": ["Plants", "Companies", "Ancient writing paper"]}, {"question": "In &quot;Paper Mario: The Thousand Year Door&quot;, what is Hooktail&#039;s weakness?", "correct_answer": "The Sound of Crickets", "incorrect_answers": ["Attacks from Koopas", "The &quot;Ice Storm&quot; Item", "The Hammer"]}, {"question": "All of the following are names of the Seven Warring States EXCEPT:", "correct_answer": "Zhai (\u7fdf)", "incorrect_answers": ["Zhao (\u8d99)", "Qin (\u79e6)", "Qi (\u9f4a)"]}, {"question": "In the Super Mario Bros. Series, what is Yoshi&#039;s scientific name?", "correct_answer": "T. Yoshisaur Munchakoopas", "incorrect_answers": ["Yoshi", "T. Yoshisotop Munchakoopas", "Yossy"]}, {"question": "What is the capital of Jamaica?", "correct_answer": "Kingston", "incorrect_answers": ["San Juan", "Port-au-Prince", "Bridgetown"]}, {"question": "How many stars are featured on New Zealand&#039;s flag?", "correct_answer": "4", "incorrect_answers": ["5", "2", "0"]}, {"question": "EDM record label Monstercat is based in which country?", "correct_answer": "Canada", "incorrect_answers": ["United States", "Australia", "United Kingdom"]}, {"question": "Which animation studio produced &quot;Log Horizon&quot;?", "correct_answer": "Satelite", "incorrect_answers": ["Sunrise", "Xebec", "Production I.G"]}, {"question": "What is the correct term for the metal object in between the CPU and the CPU fan within a computer system?", "correct_answer": "Heat Sink", "incorrect_answers": ["CPU Vent", "Temperature Decipator", "Heat Vent"]}, {"question": "Which of these is not a wonder weapon in &quot;Call Of Duty: Zombies&quot;?", "correct_answer": "R115 Resonator", "incorrect_answers": ["GKZ-45 Mk3", "Ray Gun", "Scavenger"]}]